ditchcarbon_python/__init__.py
ditchcarbon_python/auth.py
ditchcarbon_python/client.py
ditchcarbon_python/constants.py
ditchcarbon_python/resources/__init__.py
ditchcarbon_python/resources/activities.py
ditchcarbon_python/resources/base.py
ditchcarbon_python/resources/categories.py
ditchcarbon_python/resources/expenses.py
ditchcarbon_python/resources/products.py
ditchcarbon_python/resources/servers.py
ditchcarbon_python/resources/suppliers.py
ditchcarbon_python-0.1.2.dist-info/LICENSE
ditchcarbon_python-0.1.2.dist-info/METADATA
ditchcarbon_python-0.1.2.dist-info/WHEEL
ditchcarbon_python-0.1.2.dist-info/top_level.txt
ditchcarbon_python-0.1.2.dist-info/RECORD
