Metadata-Version: 2.1
Name: ditchcarbon-python
Version: 0.1.2
Summary: Official Python wrapper for the DitchCarbon API
Author-email: DitchCarbon <enquiries@ditchcarbon.com>
License: Copyright 2023 DitchCarbon
Project-URL: Source, https://github.com/ditchthis/ditchcarbon-python
Project-URL: Docs, https://docs.ditchcarbon.com
Project-URL: DitchCarbon, https://ditchcarbon.com
Keywords: ditchcarbon,API,wrapper
Classifier: License :: OSI Approved :: MIT License
Classifier: Programming Language :: Python
Classifier: Programming Language :: Python :: 3
Requires-Python: >=3.7
License-File: LICENSE
Requires-Dist: requests
Provides-Extra: dev
Requires-Dist: pytest ; extra == 'dev'
